app/__init__.py
app/core.py
autoupdate_languages2-1.2.0.dist-info/licenses/LICENSE.txt
autoupdate_languages2-1.2.0.dist-info/METADATA
autoupdate_languages2-1.2.0.dist-info/WHEEL
autoupdate_languages2-1.2.0.dist-info/entry_points.txt
autoupdate_languages2-1.2.0.dist-info/top_level.txt
autoupdate_languages2-1.2.0.dist-info/RECORD
